pyLiteracy/__init__.py
pyLiteracy/pyLiteracy.py
pyLiteracy/discord bot/pyLiteracy_discord.py
pyLiteracy/loki models/Gua_Zai/Gua_Zai.py
pyLiteracy/loki models/Gua_Zai/utteranceChecker.py
pyLiteracy/loki models/Gua_Zai/intent/Loki_Zai_Aspect.py
pyLiteracy/loki models/Gua_Zai/intent/Loki_Zai_Loc.py
pyLiteracy/loki models/Gua_Zai/intent/Loki_Zai_QMarker.py
pyLiteracy/loki models/Gua_Zai/intent/Loki_Zai_Range.py
pyLiteracy/loki models/Gua_Zai/intent/Loki_Zai_State.py
pyLiteracy/loki models/Gua_Zai/intent/Loki_Zai_idiom.py
pyLiteracy/loki models/Gua_Zai/intent/Loki_Zai_verbP.py
pyLiteracy/loki models/Gua_Zai/intent/Updater.py
pyLiteracy/loki models/Gua_Zai/intent/__init__.py
pyLiteracy/webpage/UI/UI_main.py
pyLiteracy/webpage/UI/naive_typo.py
pyLiteracy-0.0.1.dist-info/METADATA
pyLiteracy-0.0.1.dist-info/WHEEL
pyLiteracy-0.0.1.dist-info/top_level.txt
pyLiteracy-0.0.1.dist-info/RECORD
