Metadata-Version: 2.1
Name: pyLiteracy
Version: 0.0.1
Summary: A Linguistic-Based Mandarin Grammar Checker
Author-email: Chenct-jonathan <chenjonathan901210@gmail.com>
Project-URL: Homepage, https://github.com/Chenct-jonathan/pyLiteracy
Project-URL: Bug Tracker, https://github.com/Chenct-jonathan/pyLiteracy/issues
Classifier: Programming Language :: Python :: 3
Classifier: License :: OSI Approved :: MIT License
Classifier: Operating System :: OS Independent
Requires-Python: >=3.7
